CyberFloodPythonClient/CyberFlood.py
CyberFloodPythonClient/__init__.py
CyberFloodPythonClient-1.2.0.dist-info/METADATA
CyberFloodPythonClient-1.2.0.dist-info/WHEEL
CyberFloodPythonClient-1.2.0.dist-info/top_level.txt
CyberFloodPythonClient-1.2.0.dist-info/zip-safe
CyberFloodPythonClient-1.2.0.dist-info/RECORD
